{
  "relationships": [
    {
      "relationshipId": 1,
      "relationshipName": "resume",
      "otherEntityName": "resume",
      "relationshipType": "many-to-one",
      "otherEntityField": "id"
    }
  ],
  "fields": [
    {
      "fieldId": 1,
      "fieldName": "major",
      "fieldType": "String",
      "fieldValidateRules": [
        "required"
      ]
    },
    {
      "fieldId": 2,
      "fieldName": "university",
      "fieldType": "String",
      "fieldValidateRules": [
        "required"
      ]
    },
    {
      "fieldId": 3,
      "fieldName": "startTime",
      "fieldType": "ZonedDateTime",
      "fieldValidateRules": [
        "required"
      ]
    },
    {
      "fieldId": 4,
      "fieldName": "endTime",
      "fieldType": "ZonedDateTime",
      "fieldValidateRules": [
        "required"
      ]
    }
  ],
  "changelogDate": "20160507090335",
  "dto": "no",
  "pagination": "no",
  "service": "no"
}